[
  {
    "page": 1,
    "recommended_movies": [
      "Here We Are (1978)",
      "Disneyland Resort: Behind The Scenes (2010)",
      "Sunny Side of the Street (1951)",
      "Land Shark (2017)",
      "Podejrzani zakochani (2013)",
      "El Materdor (2008)",
      "Lucky U Ranch (2016)",
      "Daddy and the Muscle Academy (1991)",
      "Quand la ville s'\u00e9veille (1975)",
      "Muhammad (2015)",
      "Final Approach (1991)",
      "Sibling Rivalry (1990)",
      "Designs on Jerry (1955)",
      "Trans (1998)",
      "One last afternoon (2016)",
      "Era of Vampires, The (2003)",
      "The Other Bank (2009)",
      "Correspondences (2017)",
      "Doug's 1st Movie (1999)",
      "Sweetest Thing, The (2002)",
      "Operation Delta Force 2: Mayday (1997)",
      "Walpurgis (2015)",
      "Fallen Angel: Gram Parsons (2004)",
      "Kaminey (2009)",
      "Angel Baby (1961)",
      "Nowhere in Africa (Nirgendwo in Afrika) (2001)",
      "Notre tout petit petit mariage (2023)",
      "A Chorus of Disapproval (1989)",
      "No Stranger Than Love (2015)",
      "Wesley (2009)"
    ],
    "simulated_ratings": [
      {
        "title": "Here We Are (1978)",
        "rating": 2.0,
        "feeling": "A harmless rural farce whose slapstick and TV-movie polish left me cold.",
        "genres": [
          "Comedy",
          "TV Movie"
        ]
      },
      {
        "title": "Disneyland Resort: Behind The Scenes (2010)",
        "rating": 1.0,
        "feeling": "Feels like glossy promo material rather than a probing documentary.",
        "genres": [
          "Documentary"
        ]
      },
      {
        "title": "Sunny Side of the Street (1951)",
        "rating": 2.5,
        "feeling": "Sweet but featherweight romance that never digs beneath its setup.",
        "genres": [
          "Comedy",
          "Romance"
        ]
      },
      {
        "title": "Land Shark (2017)",
        "rating": 0.5,
        "feeling": "Goofy genre mash-up that mistakes absurdity for imagination.",
        "genres": [
          "Thriller",
          "Horror",
          "Action",
          "Adventure",
          "Comedy",
          "Science Fiction"
        ]
      },
      {
        "title": "Podejrzani zakochani (2013)",
        "rating": 2.0,
        "feeling": "High-concept dating hijinks that play too broad for my taste.",
        "genres": [
          "Comedy"
        ]
      },
      {
        "title": "El Materdor (2008)",
        "rating": 1.5,
        "feeling": "Cute in passing, but franchise fluff doesn\u2019t hold my interest.",
        "genres": [
          "Animation"
        ]
      },
      {
        "title": "Lucky U Ranch (2016)",
        "rating": 3.5,
        "feeling": "Earnest, tender coming-of-age beats that won me over despite some schmaltz.",
        "genres": [
          "Family",
          "Drama"
        ]
      },
      {
        "title": "Daddy and the Muscle Academy (1991)",
        "rating": 3.5,
        "feeling": "Candid and culturally resonant, even if the reenactments feel a bit tacky.",
        "genres": [
          "Documentary"
        ]
      },
      {
        "title": "Quand la ville s'\u00e9veille (1975)",
        "rating": 2.5,
        "feeling": "Straightforward caper mechanics with little emotional weight.",
        "genres": [
          "Crime"
        ]
      },
      {
        "title": "Muhammad (2015)",
        "rating": 4.0,
        "feeling": "Handsome, reverent storytelling whose craft and scope pulled me in.",
        "genres": [
          "History",
          "Drama"
        ]
      },
      {
        "title": "Final Approach (1991)",
        "rating": 2.5,
        "feeling": "Intriguing premise undercut by clunky execution and pulpiness.",
        "genres": [
          "Action",
          "Horror",
          "Mystery",
          "Science Fiction",
          "Thriller"
        ]
      },
      {
        "title": "Sibling Rivalry (1990)",
        "rating": 2.0,
        "feeling": "Farce built on contrivance more than character.",
        "genres": [
          "Comedy",
          "Romance"
        ]
      },
      {
        "title": "Designs on Jerry (1955)",
        "rating": 3.0,
        "feeling": "Ingenious gags and timing make this classic short pleasantly breezy.",
        "genres": [
          "Animation",
          "Comedy"
        ]
      },
      {
        "title": "Trans (1998)",
        "rating": 3.5,
        "feeling": "Lyrical, drifting mood piece that lingers more in feeling than plot.",
        "genres": [
          "Drama"
        ]
      },
      {
        "title": "One last afternoon (2016)",
        "rating": 4.0,
        "feeling": "Intimate, politically haunted conversation that feels lived-in and true.",
        "genres": [
          "Drama"
        ]
      },
      {
        "title": "Era of Vampires, The (2003)",
        "rating": 1.5,
        "feeling": "Kinetic but empty genre exercise that never engaged me.",
        "genres": [
          "Horror",
          "Fantasy",
          "Action"
        ]
      },
      {
        "title": "The Other Bank (2009)",
        "rating": 4.5,
        "feeling": "A stark, compassionate portrait of displacement that hit hard.",
        "genres": [
          "Drama"
        ]
      },
      {
        "title": "Doug's 1st Movie (1999)",
        "rating": 1.5,
        "feeling": "Lightweight kids fare that fades from memory as soon as it ends.",
        "genres": [
          "Animation",
          "Family",
          "Comedy"
        ]
      },
      {
        "title": "Sweetest Thing, The (2002)",
        "rating": 1.0,
        "feeling": "Crude antics overshadow any genuine spark.",
        "genres": [
          "Romance",
          "Comedy"
        ]
      },
      {
        "title": "Walpurgis (2015)",
        "rating": 3.5,
        "feeling": "A tense, seductive chamber piece powered by subtext.",
        "genres": [
          "Drama"
        ]
      },
      {
        "title": "Fallen Angel: Gram Parsons (2004)",
        "rating": 3.5,
        "feeling": "Insightful and affectionate without slipping into hagiography.",
        "genres": [
          "Documentary",
          "Music"
        ]
      },
      {
        "title": "Kaminey (2009)",
        "rating": 2.5,
        "feeling": "Energetic but overcooked, with style crowding out substance.",
        "genres": [
          "Action",
          "Crime",
          "Drama"
        ]
      },
      {
        "title": "Angel Baby (1961)",
        "rating": 3.5,
        "feeling": "A sober look at faith and exploitation that stays quietly affecting.",
        "genres": [
          "Drama"
        ]
      },
      {
        "title": "Nowhere in Africa (Nirgendwo in Afrika) (2001)",
        "rating": 4.0,
        "feeling": "Nuanced, humane exile story with a strong emotional core.",
        "genres": [
          "Drama"
        ]
      },
      {
        "title": "Notre tout petit petit mariage (2023)",
        "rating": 1.5,
        "feeling": "Loud, chaotic wedding hijinks aren\u2019t my scene.",
        "genres": [
          "Comedy"
        ]
      },
      {
        "title": "A Chorus of Disapproval (1989)",
        "rating": 2.5,
        "feeling": "Mildly witty but too slight to leave a mark.",
        "genres": [
          "Drama",
          "Comedy",
          "Romance"
        ]
      },
      {
        "title": "No Stranger Than Love (2015)",
        "rating": 1.5,
        "feeling": "Quirk for quirk\u2019s sake left me unmoved.",
        "genres": [
          "Romance",
          "Comedy"
        ]
      },
      {
        "title": "Wesley (2009)",
        "rating": 2.0,
        "feeling": "Worthy subject, preachy treatment.",
        "genres": [
          "History",
          "Drama"
        ]
      }
    ]
  },
  {
    "page": 2,
    "recommended_movies": [
      "Morning Light (2008)",
      "Switching Channels (1988)",
      "The Pirate Fairy (2014)",
      "A Spot of Bother (2010)",
      "The Simpsons in Plusaversary (2021)",
      "Lake Nowhere (2014)",
      "One Man's Justice (1996)",
      "Flesh (1968)",
      "Mantervention (2014)",
      "Forbidden Love Game (1975)",
      "How I Became a Superhero (2020)",
      "Mon oncle d'Am\u00e9rique (1980)",
      "Magnificent Bodyguards (Fei du juan yun shan) (1978)",
      "Global Meltdown (2017)",
      "Maigret (2022)",
      "Destiny in Space (1994)",
      "Distant Voices, Still Lives (1988)",
      "Girl Shy (1924)",
      "Tweety's High Flying Adventure (2000)",
      "Leonor Will Never Die (2022)",
      "Since Otar Left (Depuis qu'Otar est parti...) (2003)",
      "Candy (1968)",
      "Puppet Master: Axis Termination (2017)",
      "Sniper: Rogue Mission (2022)",
      "Soorarai Pottru (2020)",
      "Die Ungewollten - Die Irrfahrt der St. Louis (2019)",
      "What Every Frenchwoman Wants (1986)",
      "Body Keepers (2018)",
      "Tony Manero (2008)",
      "Whatever Happened to Aunt Alice? (1969)"
    ],
    "simulated_ratings": [
      {
        "title": "Morning Light (2008)",
        "rating": 2.0,
        "feeling": "Handsome but glossy sailing promo with little to chew on.",
        "genres": [
          "Documentary"
        ]
      },
      {
        "title": "Switching Channels (1988)",
        "rating": 2.5,
        "feeling": "Breezy screwball sparks, thin on genuine bite.",
        "genres": [
          "Comedy"
        ]
      },
      {
        "title": "The Pirate Fairy (2014)",
        "rating": 1.5,
        "feeling": "Cute but disposable franchise fluff.",
        "genres": [
          "Animation",
          "Family"
        ]
      },
      {
        "title": "A Spot of Bother (2010)",
        "rating": 3.0,
        "feeling": "Wry, lightly affecting family chaos that goes down easy.",
        "genres": [
          "Comedy"
        ]
      },
      {
        "title": "The Simpsons in Plusaversary (2021)",
        "rating": 1.0,
        "feeling": "Brand mash-up gags masquerading as a story.",
        "genres": [
          "Animation",
          "Comedy",
          "Fantasy"
        ]
      },
      {
        "title": "Lake Nowhere (2014)",
        "rating": 1.5,
        "feeling": "Retro-slasher pastiche with more wink than substance.",
        "genres": [
          "Comedy",
          "Horror"
        ]
      },
      {
        "title": "One Man's Justice (1996)",
        "rating": 2.0,
        "feeling": "Routine vigilante beats without much texture.",
        "genres": [
          "Action",
          "Thriller"
        ]
      },
      {
        "title": "Flesh (1968)",
        "rating": 1.5,
        "feeling": "Aimless decadence that left me more numb than moved.",
        "genres": [
          "Drama"
        ]
      },
      {
        "title": "Mantervention (2014)",
        "rating": 1.0,
        "feeling": "Bro-y hijinks with little charm or insight.",
        "genres": [
          "Romance",
          "Comedy"
        ]
      },
      {
        "title": "Forbidden Love Game (1975)",
        "rating": 1.5,
        "feeling": "Sleazy power-play posing as provocation, not for me.",
        "genres": [
          "Comedy",
          "Crime",
          "Drama"
        ]
      },
      {
        "title": "How I Became a Superhero (2020)",
        "rating": 3.0,
        "feeling": "Grounded enough to engage me despite the caped trappings.",
        "genres": [
          "Science Fiction",
          "Adventure",
          "Action",
          "Comedy",
          "Thriller"
        ]
      },
      {
        "title": "Mon oncle d'Am\u00e9rique (1980)",
        "rating": 4.0,
        "feeling": "A curious, humane weave of theory and life that resonated.",
        "genres": [
          "Comedy",
          "Drama",
          "Romance"
        ]
      },
      {
        "title": "Magnificent Bodyguards (Fei du juan yun shan) (1978)",
        "rating": 2.0,
        "feeling": "Brisk fists, thin stakes\u2014diverting but forgettable.",
        "genres": [
          "Action"
        ]
      },
      {
        "title": "Global Meltdown (2017)",
        "rating": 1.0,
        "feeling": "Cheap disaster thrills with no human pulse.",
        "genres": [
          "Action",
          "Science Fiction",
          "Thriller",
          "TV Movie"
        ]
      },
      {
        "title": "Maigret (2022)",
        "rating": 3.5,
        "feeling": "Somber, humane procedural where the mood lingers.",
        "genres": [
          "Mystery",
          "Drama"
        ]
      },
      {
        "title": "Destiny in Space (1994)",
        "rating": 3.0,
        "feeling": "Stirring cosmic imagery, light on depth.",
        "genres": [
          "Documentary"
        ]
      },
      {
        "title": "Distant Voices, Still Lives (1988)",
        "rating": 4.0,
        "feeling": "A bruised, lyrical family portrait that quietly floored me.",
        "genres": [
          "Drama",
          "Music"
        ]
      },
      {
        "title": "Girl Shy (1924)",
        "rating": 3.0,
        "feeling": "Endearing craft whose bravura finale outweighs the corn.",
        "genres": [
          "Comedy",
          "Romance"
        ]
      },
      {
        "title": "Tweety's High Flying Adventure (2000)",
        "rating": 1.5,
        "feeling": "Stretched-out antics that wear thin fast.",
        "genres": [
          "Animation",
          "Family",
          "Comedy",
          "Fantasy"
        ]
      },
      {
        "title": "Leonor Will Never Die (2022)",
        "rating": 3.0,
        "feeling": "Playful meta-odyssey with enough heart to ground the whimsy.",
        "genres": [
          "Fantasy",
          "Comedy",
          "Action",
          "Drama"
        ]
      },
      {
        "title": "Since Otar Left (Depuis qu'Otar est parti...) (2003)",
        "rating": 4.5,
        "feeling": "Tender, truthful, and devastating in the smallest gestures.",
        "genres": [
          "Drama"
        ]
      },
      {
        "title": "Candy (1968)",
        "rating": 1.0,
        "feeling": "Smirking, dated sexcapade that left me bored.",
        "genres": [
          "Adventure",
          "Comedy",
          "Fantasy"
        ]
      },
      {
        "title": "Puppet Master: Axis Termination (2017)",
        "rating": 0.5,
        "feeling": "Shoddy franchise schlock with zero bite.",
        "genres": [
          "Fantasy",
          "Horror",
          "War"
        ]
      },
      {
        "title": "Sniper: Rogue Mission (2022)",
        "rating": 1.5,
        "feeling": "Generic potboiler going through the motions.",
        "genres": [
          "Action",
          "Thriller",
          "Mystery"
        ]
      },
      {
        "title": "Soorarai Pottru (2020)",
        "rating": 3.5,
        "feeling": "Rousing, big-hearted saga that hits more than it hammers.",
        "genres": [
          "Drama",
          "Action"
        ]
      },
      {
        "title": "Die Ungewollten - Die Irrfahrt der St. Louis (2019)",
        "rating": 4.0,
        "feeling": "Clear, humane recounting that stings with relevance.",
        "genres": [
          "Documentary",
          "History",
          "TV Movie",
          "Drama"
        ]
      },
      {
        "title": "What Every Frenchwoman Wants (1986)",
        "rating": 0.5,
        "feeling": "Leering, ugly fantasy masquerading as coming-of-age.",
        "genres": [
          "Comedy",
          "Drama"
        ]
      },
      {
        "title": "Body Keepers (2018)",
        "rating": 1.0,
        "feeling": "Derivative teen chiller with no scares or soul.",
        "genres": [
          "Thriller"
        ]
      },
      {
        "title": "Tony Manero (2008)",
        "rating": 3.5,
        "feeling": "A queasy, compelling character study that got under my skin.",
        "genres": [
          "Drama"
        ]
      }
    ]
  },
  {
    "page": 3,
    "recommended_movies": [
      "Circumstances 2: The Chase (2020)",
      "Slaughter (1972)",
      "Fyre Fraud (2019)",
      "Jackie & Ryan (2015)",
      "Four Rode Out (1970)",
      "Mali Twist (2022)",
      "Case 39 (2009)",
      "My Dear Secretary (1948)",
      "Moro Witch Doctor (1964)",
      "Manifesto (1988)",
      "Mubarakan (2017)",
      "Beneath (2007)",
      "The Perfect Wedding (2012)",
      "Arthur (2011)",
      "Choke (1999)",
      "The Hip Hop Nutcracker (2022)",
      "Hey... Stop Stabbing Me! (2003)",
      "\u0414\u0435\u043c\u0438\u0434\u043e\u0432\u044b (1983)",
      "My Bromance (2014)",
      "The Gift (2014)",
      "Visitor Q (Bizita Q) (2001)",
      "Winter's Bone (2010)",
      "Iron Man 2 (2010)",
      "War Lord, The (1965)",
      "Diaspora (2022)",
      "Contraband (2012)",
      "Demolition University (1997)",
      "Great Freedom (2021)",
      "Audition (\u00d4dishon) (1999)",
      "One Dark Night (1983)"
    ],
    "simulated_ratings": [
      {
        "title": "Circumstances 2: The Chase (2020)",
        "rating": 1.5,
        "feeling": "Low-budget crime-thriller grind with lots of plot and little human pulse.",
        "genres": [
          "Drama"
        ]
      },
      {
        "title": "Slaughter (1972)",
        "rating": 2.0,
        "feeling": "Blunt revenge beats and fed-mandated detours kept me at arm\u2019s length.",
        "genres": [
          "Action",
          "Crime",
          "Drama"
        ]
      },
      {
        "title": "Fyre Fraud (2019)",
        "rating": 3.0,
        "feeling": "Slick, entertaining post-mortem with bite, if short on deeper reckoning.",
        "genres": [
          "Documentary"
        ]
      },
      {
        "title": "Mali Twist (2022)",
        "rating": 4.0,
        "feeling": "Romance and revolution entwine with warmth and melancholy that moved me.",
        "genres": [
          "Drama"
        ]
      },
      {
        "title": "Case 39 (2009)",
        "rating": 1.5,
        "feeling": "Jump-scare parenting parable that substitutes noise for dread.",
        "genres": [
          "Horror",
          "Mystery",
          "Thriller"
        ]
      },
      {
        "title": "My Dear Secretary (1948)",
        "rating": 2.5,
        "feeling": "Pleasantly fizzy, but the gender games feel thin and dated.",
        "genres": [
          "Drama",
          "Romance",
          "Comedy"
        ]
      },
      {
        "title": "Moro Witch Doctor (1964)",
        "rating": 2.0,
        "feeling": "Pulp adventure tropes and ugly stereotypes make it hard to invest.",
        "genres": [
          "Action",
          "Adventure"
        ]
      },
      {
        "title": "Manifesto (1988)",
        "rating": 3.0,
        "feeling": "A wry miniature of power and farce that amuses more than it resonates.",
        "genres": [
          "Comedy",
          "Drama",
          "Romance"
        ]
      },
      {
        "title": "Mubarakan (2017)",
        "rating": 2.0,
        "feeling": "Loud, sprawling hijinks with enough heart but too much bloat.",
        "genres": [
          "Comedy",
          "Drama"
        ]
      },
      {
        "title": "Beneath (2007)",
        "rating": 1.5,
        "feeling": "Generic guilt-haunted chills that never found a convincing pulse.",
        "genres": [
          "Horror",
          "Mystery",
          "Thriller"
        ]
      },
      {
        "title": "The Perfect Wedding (2012)",
        "rating": 2.5,
        "feeling": "Agreeably cozy and harmless, if featherweight and tidy.",
        "genres": [
          "Comedy"
        ]
      },
      {
        "title": "Arthur (2011)",
        "rating": 2.0,
        "feeling": "Glossy, glib charm offensive that never earns its sentiment.",
        "genres": [
          "Comedy",
          "Romance"
        ]
      },
      {
        "title": "Choke (1999)",
        "rating": 3.0,
        "feeling": "Candid, engaging fight prep doc that favors presence over insight.",
        "genres": [
          "Documentary"
        ]
      },
      {
        "title": "The Hip Hop Nutcracker (2022)",
        "rating": 1.5,
        "feeling": "Cheery brand-ready mashup that felt more concept than feeling.",
        "genres": [
          "Music",
          "Comedy",
          "Family"
        ]
      },
      {
        "title": "Hey... Stop Stabbing Me! (2003)",
        "rating": 1.5,
        "feeling": "Goofy, self-aware chaos that mistakes absurdity for wit.",
        "genres": [
          "Comedy",
          "Horror"
        ]
      },
      {
        "title": "\u0414\u0435\u043c\u0438\u0434\u043e\u0432\u044b (1983)",
        "rating": 3.0,
        "feeling": "Stately, serviceable history-play texture more than lived-in drama.",
        "genres": [
          "Drama",
          "TV Movie",
          "History"
        ]
      },
      {
        "title": "My Bromance (2014)",
        "rating": 3.0,
        "feeling": "Sweet, earnest coming-of-age melodrama that mostly works despite the gloss.",
        "genres": [
          "Comedy",
          "Drama"
        ]
      },
      {
        "title": "The Gift (2014)",
        "rating": 3.0,
        "feeling": "A tender, small-scale spark that finds quiet feeling in simple gestures.",
        "genres": [
          "Romance",
          "Drama"
        ]
      },
      {
        "title": "Winter's Bone (2010)",
        "rating": 4.0,
        "feeling": "Flinty, humane survival story that gripped me.",
        "genres": [
          "Drama",
          "Mystery"
        ]
      },
      {
        "title": "Iron Man 2 (2010)",
        "rating": 2.5,
        "feeling": "Clattery franchise momentum with just enough character grace notes.",
        "genres": [
          "Adventure",
          "Action",
          "Science Fiction"
        ]
      },
      {
        "title": "War Lord, The (1965)",
        "rating": 3.0,
        "feeling": "Measured, moody period piece where duty and desire rub raw.",
        "genres": [
          "History",
          "Drama",
          "War"
        ]
      },
      {
        "title": "Diaspora (2022)",
        "rating": 3.5,
        "feeling": "A sharp, unsettling spin on gentrification that lands its social sting.",
        "genres": []
      },
      {
        "title": "Contraband (2012)",
        "rating": 2.5,
        "feeling": "Competent, forgettable potboiler that hustles without much texture.",
        "genres": [
          "Thriller",
          "Action",
          "Drama",
          "Crime"
        ]
      },
      {
        "title": "Demolition University (1997)",
        "rating": 1.5,
        "feeling": "Cheap, boilerplate thrills with no real stakes or wit.",
        "genres": [
          "Action",
          "Thriller"
        ]
      },
      {
        "title": "Great Freedom (2021)",
        "rating": 4.5,
        "feeling": "Quietly devastating, humane, and tender in all the right ways.",
        "genres": [
          "Drama",
          "Romance",
          "Crime"
        ]
      }
    ]
  },
  {
    "page": 4,
    "recommended_movies": [
      "De Scheepsjongens Van Bontekoe (2007)",
      "Entertaining Christmas (2018)",
      "Once in a Summer (2006)",
      "Arson Mom (2014)",
      "The Quatermass Experiment (2005)",
      "Dinosaur Island (1994)",
      "Bad Ben - The Mandela Effect (2018)",
      "Meet the Feebles (1989)",
      "Stripper (1986)",
      "Longshots, The (2008)",
      "Sociopathia (2015)",
      "Handmaid's Tale, The (1990)",
      "Lucky Luke (1991)",
      "The Black Shield Of Falworth (1954)",
      "Boots on the Ground (2017)",
      "La malcasada (1927)",
      "Rocking Horse Winner, The (1950)",
      "Judge Dredd (1995)",
      "Penny Princess (1952)",
      "Hara Hara Mahadevaki (2017)",
      "Julius Caesar (1950)",
      "Evidence (2011)",
      "Grimewave: Cockface III (2013)",
      "With You The World Is Fun (1982)",
      "Ella Cinders (1926)",
      "Dara Ju (2017)",
      "Forsaken, The (2001)",
      "Manchester United: For the Glory (2020)",
      "The White Viking (1991)",
      "Locusts: The 8th Plague (2005)"
    ],
    "simulated_ratings": [
      {
        "title": "De Scheepsjongens Van Bontekoe (2007)",
        "rating": 2.0,
        "feeling": "Brisk colonial yarn with thin characterization and dated beats.",
        "genres": [
          "Adventure",
          "History"
        ]
      },
      {
        "title": "Entertaining Christmas (2018)",
        "rating": 1.5,
        "feeling": "Glossy, prefab holiday comfort with little real feeling.",
        "genres": [
          "TV Movie",
          "Romance",
          "Family"
        ]
      },
      {
        "title": "Once in a Summer (2006)",
        "rating": 4.0,
        "feeling": "Wistful, tender melodrama that earns its ache.",
        "genres": [
          "Drama",
          "Romance"
        ]
      },
      {
        "title": "Arson Mom (2014)",
        "rating": 1.5,
        "feeling": "Lifetime-y contrivances and flat craft kept me at arm's length.",
        "genres": [
          "Thriller",
          "TV Movie"
        ]
      },
      {
        "title": "The Quatermass Experiment (2005)",
        "rating": 3.0,
        "feeling": "Atmospheric, talky sci-fi that intrigues more than it thrills.",
        "genres": [
          "Science Fiction",
          "Drama",
          "Thriller",
          "TV Movie"
        ]
      },
      {
        "title": "Dinosaur Island (1994)",
        "rating": 0.5,
        "feeling": "Leering, cheesy pulp that bored and annoyed me.",
        "genres": [
          "Adventure",
          "Comedy",
          "Fantasy"
        ]
      },
      {
        "title": "Bad Ben - The Mandela Effect (2018)",
        "rating": 0.5,
        "feeling": "Threadbare meta-gag stretched past breaking.",
        "genres": [
          "Comedy",
          "Horror"
        ]
      },
      {
        "title": "Meet the Feebles (1989)",
        "rating": 1.5,
        "feeling": "Grotesque, smirking satire whose shock wears thin fast.",
        "genres": [
          "Comedy",
          "Music",
          "Fantasy"
        ]
      },
      {
        "title": "Stripper (1986)",
        "rating": 0.5,
        "feeling": "Sleazy novelty with zero art or feeling.",
        "genres": []
      },
      {
        "title": "Longshots, The (2008)",
        "rating": 3.0,
        "feeling": "Earnest, feel-good uplift that hits enough honest notes.",
        "genres": [
          "Drama",
          "Family",
          "Comedy"
        ]
      },
      {
        "title": "Sociopathia (2015)",
        "rating": 1.5,
        "feeling": "Grim psychodrama undercut by amateur sheen and empty provocation.",
        "genres": [
          "Horror"
        ]
      },
      {
        "title": "Handmaid's Tale, The (1990)",
        "rating": 3.5,
        "feeling": "Chilling premise lands enough despite blunt edges.",
        "genres": [
          "Drama",
          "Science Fiction"
        ]
      },
      {
        "title": "Lucky Luke (1991)",
        "rating": 2.0,
        "feeling": "Goofy, lightweight romp that breezes by without much bite.",
        "genres": [
          "Comedy",
          "Western"
        ]
      },
      {
        "title": "The Black Shield Of Falworth (1954)",
        "rating": 2.5,
        "feeling": "Sturdy pageantry, thin emotion.",
        "genres": [
          "Adventure",
          "History",
          "Romance"
        ]
      },
      {
        "title": "Boots on the Ground (2017)",
        "rating": 1.5,
        "feeling": "War-horror hybrid with more noise than dread.",
        "genres": [
          "Horror"
        ]
      },
      {
        "title": "La malcasada (1927)",
        "rating": 3.0,
        "feeling": "Melodramatic but fascinating as a time capsule.",
        "genres": [
          "Drama"
        ]
      },
      {
        "title": "Judge Dredd (1995)",
        "rating": 2.0,
        "feeling": "Loud, plasticky dystopia with fleeting pulp fun.",
        "genres": [
          "Science Fiction",
          "Action"
        ]
      },
      {
        "title": "Penny Princess (1952)",
        "rating": 2.5,
        "feeling": "Pleasant fluff with charm but little spark.",
        "genres": [
          "Comedy",
          "Romance"
        ]
      },
      {
        "title": "Hara Hara Mahadevaki (2017)",
        "rating": 2.0,
        "feeling": "Loud, labored farce that wears thin.",
        "genres": [
          "Romance",
          "Comedy",
          "Drama"
        ]
      },
      {
        "title": "Julius Caesar (1950)",
        "rating": 3.5,
        "feeling": "Measured, potent oratory that still lands.",
        "genres": [
          "Drama",
          "History"
        ]
      },
      {
        "title": "Evidence (2011)",
        "rating": 1.5,
        "feeling": "Found-footage jitters without a human pulse.",
        "genres": [
          "Horror"
        ]
      },
      {
        "title": "Grimewave: Cockface III (2013)",
        "rating": 0.5,
        "feeling": "Juvenile gross-out shtick that mistakes provocation for wit.",
        "genres": [
          "Comedy",
          "Horror"
        ]
      },
      {
        "title": "Ella Cinders (1926)",
        "rating": 3.0,
        "feeling": "Spry, endearing rags-to-reel fable that goes down easy.",
        "genres": [
          "Romance",
          "Comedy"
        ]
      },
      {
        "title": "Dara Ju (2017)",
        "rating": 3.5,
        "feeling": "Clear-eyed, empathetic character study with real stakes.",
        "genres": [
          "Crime",
          "Drama"
        ]
      },
      {
        "title": "Forsaken, The (2001)",
        "rating": 1.5,
        "feeling": "Glossy vampire road-chiller that never finds a pulse.",
        "genres": [
          "Horror",
          "Thriller"
        ]
      },
      {
        "title": "Manchester United: For the Glory (2020)",
        "rating": 1.5,
        "feeling": "Brand-burnished highlight reel more than a documentary.",
        "genres": [
          "Documentary"
        ]
      },
      {
        "title": "The White Viking (1991)",
        "rating": 3.0,
        "feeling": "Rugged, morally knotted saga that engaged me despite the rough edges.",
        "genres": [
          "Drama",
          "Adventure"
        ]
      },
      {
        "title": "Locusts: The 8th Plague (2005)",
        "rating": 1.0,
        "feeling": "Cheap creature-feature mayhem with no human core.",
        "genres": [
          "Drama",
          "Horror"
        ]
      }
    ]
  }
]